<?xml version="1.0" encoding="UTF-8"?>
<objects serializationModel="Studio.02.02.00">
	<object class="MixerGroup" id="{ae09eb87-6288-44e2-a9f7-964fad13df75}">
		<property name="volume">
			<value>-14</value>
		</property>
		<property name="name">
			<value>Throw</value>
		</property>
		<relationship name="effectChain">
			<destination>{6c3cc5ac-17d6-4f75-ab15-ae7bbaefb76d}</destination>
		</relationship>
		<relationship name="panner">
			<destination>{98028286-73e0-4233-9387-92bf8c34e0df}</destination>
		</relationship>
		<relationship name="output">
			<destination>{609a3249-d80e-49b5-8308-07e31699fd7e}</destination>
		</relationship>
	</object>
	<object class="MixerBusEffectChain" id="{6c3cc5ac-17d6-4f75-ab15-ae7bbaefb76d}">
		<relationship name="effects">
			<destination>{68123003-89f7-4201-9297-1e6ee41d2706}</destination>
			<destination>{00425471-3e3d-4982-b58d-a66264f8d52c}</destination>
		</relationship>
	</object>
	<object class="MixerBusPanner" id="{98028286-73e0-4233-9387-92bf8c34e0df}" />
	<object class="MixerSend" id="{68123003-89f7-4201-9297-1e6ee41d2706}">
		<property name="inputFormat">
			<value>1</value>
		</property>
		<relationship name="mixerReturn">
			<destination>{3148f651-0985-44b8-8719-c113951996b4}</destination>
		</relationship>
	</object>
	<object class="MixerBusFader" id="{00425471-3e3d-4982-b58d-a66264f8d52c}" />
</objects>
