<?xml version="1.0" encoding="UTF-8"?>
<objects serializationModel="Studio.02.02.00">
	<object class="MixerGroup" id="{c940af6f-76a6-487d-970c-1ccf3c9a248e}">
		<property name="name">
			<value>Lotus</value>
		</property>
		<relationship name="effectChain">
			<destination>{09c8c21c-d3a9-4fd2-b64a-9449f7be6806}</destination>
		</relationship>
		<relationship name="panner">
			<destination>{7d28c819-660d-4515-bfb0-e82af4fdffb3}</destination>
		</relationship>
		<relationship name="output">
			<destination>{96d55050-3dcd-4570-bab7-e0034359a861}</destination>
		</relationship>
	</object>
	<object class="MixerBusEffectChain" id="{09c8c21c-d3a9-4fd2-b64a-9449f7be6806}">
		<relationship name="effects">
			<destination>{351074be-07c0-42eb-bcdc-76825128a9d5}</destination>
		</relationship>
	</object>
	<object class="MixerBusPanner" id="{7d28c819-660d-4515-bfb0-e82af4fdffb3}" />
	<object class="MixerBusFader" id="{351074be-07c0-42eb-bcdc-76825128a9d5}" />
</objects>
