<?xml version="1.0" encoding="UTF-8"?>
<objects serializationModel="Studio.02.02.00">
	<object class="ParameterPreset" id="{068e1dba-8d9a-40ae-802c-241b703dce8a}">
		<property name="note" />
		<property name="name">
			<value>FOREST_7</value>
		</property>
		<relationship name="folder">
			<destination>{43362e55-39de-4dd0-b180-0ba806a276c4}</destination>
		</relationship>
		<relationship name="parameter">
			<destination>{d3a7e42c-26b2-4e31-a632-83bea0a54e56}</destination>
		</relationship>
	</object>
	<object class="GameParameter" id="{d3a7e42c-26b2-4e31-a632-83bea0a54e56}">
		<property name="initialValue">
			<value>0</value>
		</property>
	</object>
</objects>
