<?xml version="1.0" encoding="UTF-8"?>
<objects serializationModel="Studio.02.02.00">
	<object class="ParameterPreset" id="{efc7e2e4-842f-43fc-bcc3-e235e09a7b84}">
		<property name="note" />
		<property name="name">
			<value>FOREST_6</value>
		</property>
		<relationship name="folder">
			<destination>{43362e55-39de-4dd0-b180-0ba806a276c4}</destination>
		</relationship>
		<relationship name="parameter">
			<destination>{264b899d-d1ea-4869-9c92-1bf34cd8ec38}</destination>
		</relationship>
	</object>
	<object class="GameParameter" id="{264b899d-d1ea-4869-9c92-1bf34cd8ec38}">
		<property name="initialValue">
			<value>0</value>
		</property>
	</object>
</objects>
