<?xml version="1.0" encoding="UTF-8"?>
<objects serializationModel="Studio.02.02.00">
	<object class="AudioFile" id="{660186ed-d168-43cd-ab7e-abdf1bec952c}">
		<property name="assetPath">
			<value>SFX/Environment/Lotus/Pulse/Crunch/SFX_Lotus_Crunch_2.mp3</value>
		</property>
		<property name="frequencyInKHz">
			<value>44.0999985</value>
		</property>
		<property name="channelCount">
			<value>2</value>
		</property>
		<property name="length">
			<value>2.5338775510204083</value>
		</property>
		<relationship name="masterAssetFolder">
			<destination>{560c1fc5-9344-4645-a10e-3fa9049baa01}</destination>
		</relationship>
	</object>
</objects>
