<?xml version="1.0" encoding="UTF-8"?>
<objects serializationModel="Studio.02.02.00">
	<object class="AudioFile" id="{d892bb5a-44d8-41d9-9b62-32afd4c0bebd}">
		<property name="assetPath">
			<value>Title Theme.wav</value>
		</property>
		<property name="isStreaming">
			<value>true</value>
		</property>
		<property name="frequencyInKHz">
			<value>44.0999985</value>
		</property>
		<property name="channelCount">
			<value>2</value>
		</property>
		<property name="length">
			<value>153.60002267573697</value>
		</property>
		<relationship name="masterAssetFolder">
			<destination>{560c1fc5-9344-4645-a10e-3fa9049baa01}</destination>
		</relationship>
	</object>
</objects>
